volatilipy/__init__.py
volatilipy/helper_functions.py
volatilipy/options_data.py
volatilipy/volatility_surface.py
volatilipy-0.1.4.dist-info/AUTHORS.rst
volatilipy-0.1.4.dist-info/LICENSE
volatilipy-0.1.4.dist-info/METADATA
volatilipy-0.1.4.dist-info/WHEEL
volatilipy-0.1.4.dist-info/top_level.txt
volatilipy-0.1.4.dist-info/RECORD
