Metadata-Version: 2.1
Name: volatilipy
Version: 0.1.4
Summary: Wrappers around Quantlib and Pandas to faciliate the creation of volatility surfaces for equity option valuations
Home-page: https://github.com/aaronsmith1234/volatilipy
Author: Aaron Smith
Author-email: aaronsmith1234@gmail.com
License: MIT license
Keywords: volatilipy
Platform: UNKNOWN
Classifier: Development Status :: 2 - Pre-Alpha
Classifier: Intended Audience :: Developers
Classifier: License :: OSI Approved :: MIT License
Classifier: Natural Language :: English
Classifier: Programming Language :: Python :: 3
Classifier: Programming Language :: Python :: 3.7
Classifier: Programming Language :: Python :: 3.8
Classifier: Programming Language :: Python :: 3.9
Requires-Python: >=3.5
Requires-Dist: pandas (>=1.3.4)
Requires-Dist: QuantLib (>=1.24)
